[
  {
    "name": "QRev",
    "organization": "U.S. Geological Survey",
    "description": "Python versions of QRev",
    "version": "4.16",
    "status": "Development",

    "permissions": {
      "usageType": "openSource",
      "licenses": [
        {
          "name": "Public Domain, CC0-1.0",
          "URL": "https://code.usgs.gov/QRev/QRevPy/-/blob/master/LICENSE.md"
        }
      ]
    },

    "homepageURL": "https://code.usgs.gov/QRev/QRevPy",
    "downloadURL": "https://code.usgs.gov/QRev/QRevPy/-/archive/master/QRevPy-master.zip",
    "disclaimerURL": "https://code.usgs.gov/QRev/QRevPy/-/blob/master/DISCLAIMER.md",
    "repositoryURL": "https://code.usgs.gov/QRev/QRevPy.git",
    "vcs": "git",

    "laborHours": 2000,

    "tags": [
      "QRev",
	  "Discharge",
	  "Streamflow",
      "ADCP"
    ],

    "languages": [
      "Python"
    ],

    "contact": {
      "name": "David S Mueller",
      "email": "dmueller@usgs.gov"
    },

    "date": {
      "metadataLastUpdated": "2020-06-22"
    }
  }
]
